[
    {
        "name": "USDT",
        "symbol": "USDT",
        "address":{
            "0x61":"0xED3bD1e051bEFCc33d289c3FB9aAE392ee7Fb016"
        }
        ,
        "decimals":18,
        "icon":"https://icons.iconarchive.com/icons/cjdowner/cryptocurrency-flat/1024/Tether-USDT-icon.png"
    },
    {
        "name": "CRPLAY",
        "symbol": "CRPLAY",
        "address":{
            "0x61":"0xcfC4814B4Ea0B9C250d10651241741817f1f1121"
        }
        ,
        "decimals":10,
        "icon":"https://i.ibb.co/rtnGWdB/Group-26-1.png"
    }
]
